pyHana/__init__.py
pyHana/analysis/__init__.py
pyHana/analysis/backtest.py
pyHana/analysis/condSearch.py
pyHana/analysis/findSignals.py
pyHana/analysis/func.py
pyHana/analysis/graph.py
pyHana/analysis/movingAverage.py
pyHana/analysis/parallel.py
pyHana/analysis/stockEcoIndex.py
pyHana/common/__init__.py
pyHana/common/code.py
pyHana/common/conf.py
pyHana/common/dataProc.py
pyHana/common/graph.py
pyHana/common/urlProc.py
pyHana/dataSync/__init__.py
pyHana/dataSync/dartSync.py
pyHana/dataSync/dartSyncFile.py
pyHana/dataSync/ebestSync.py
pyHana/dataSync/finInfoSync.py
pyHana/dataSync/kindSync.py
pyHana/dataSync/marketIndexSync.py
pyHana/dataSync/naverSync.py
pyHana/dataSync/tradeviewSync.py
pyHana/dataSync/yahooSync.py
pyHana/innerIO/__init__.py
pyHana/innerIO/companyInfo.py
pyHana/innerIO/marketIndex.py
pyHana/innerIO/parallel.py
pyHana/innerIO/stockInfo.py
pyHana/innerIO/tradeview.py
pyHana/outerIO/__init__.py
pyHana/outerIO/companyInfo.py
pyHana/outerIO/dart.py
pyHana/outerIO/ebest.py
pyHana/outerIO/kind.py
pyHana/outerIO/marketIndex.py
pyHana/outerIO/naver.py
pyHana/outerIO/tradeview.py
pyHana/outerIO/yahoo.py
pyhana-1.0.0.dist-info/METADATA
pyhana-1.0.0.dist-info/WHEEL
pyhana-1.0.0.dist-info/top_level.txt
pyhana-1.0.0.dist-info/RECORD
