Metadata-Version: 2.1
Name: pyhana
Version: 1.0.0
Summary: for pyhana club members
Home-page: https://github.com/pyhana/pyhana
Author: pyhanclub
Author-email: pyhanclub@gmail.com
License: UNKNOWN
Keywords: pyhanclub
Platform: UNKNOWN
Classifier: Programming Language :: Python :: 3.6
Classifier: Programming Language :: Python :: 3.7
Classifier: Programming Language :: Python :: 3.8
Classifier: Programming Language :: Python :: 3.9
Classifier: Programming Language :: Python :: 3.10
Classifier: Programming Language :: Python :: 3.11
Requires-Python: >=3
Requires-Dist: pandas
Requires-Dist: configparser
Requires-Dist: requests
Requires-Dist: bs4
